{"_type":"export","__export_format":4,"__export_date":"2021-04-22T23:03:21.774Z","__export_source":"insomnia.desktop.app:v2020.5.2","resources":[{"_id":"req_712c096af4e24828867ab706ac89a230","parentId":"fld_7c17905fe9454434a797cd6b98505b63","modified":1619132105093,"created":1619131967596,"url":"{{ _.BaseURL }}/users","name":"findAll","description":"","method":"GET","body":{},"parameters":[],"headers":[],"authentication":{},"metaSortKey":-1619132099625,"isPrivate":false,"settingStoreCookies":true,"settingSendCookies":true,"settingDisableRenderRequestBody":false,"settingEncodeUrl":true,"settingRebuildPath":true,"settingFollowRedirects":"global","_type":"request"},{"_id":"fld_7c17905fe9454434a797cd6b98505b63","parentId":"wrk_2a18ee995e4e460d8a576e4d8fe5852b","modified":1618944885686,"created":1618944885686,"name":"user","description":"","environment":{},"environmentPropertyOrder":null,"metaSortKey":-1618944885686,"_type":"request_group"},{"_id":"wrk_2a18ee995e4e460d8a576e4d8fe5852b","parentId":null,"modified":1618857521724,"created":1618857521724,"name":"trainee itatech 2021","description":"","scope":"collection","_type":"workspace"},{"_id":"req_a07fedf2166146518bf87d5d9afb70f7","parentId":"fld_7c17905fe9454434a797cd6b98505b63","modified":1619132107099,"created":1619132069410,"url":"{{ _.BaseURL }}/users/1","name":"findOneById","description":"","method":"GET","body":{},"parameters":[],"headers":[],"authentication":{},"metaSortKey":-1619132099600,"isPrivate":false,"settingStoreCookies":true,"settingSendCookies":true,"settingDisableRenderRequestBody":false,"settingEncodeUrl":true,"settingRebuildPath":true,"settingFollowRedirects":"global","_type":"request"},{"_id":"req_1eeb202301cc49e29227ea78e137ed7e","parentId":"fld_7c17905fe9454434a797cd6b98505b63","modified":1619132103047,"created":1618944903941,"url":"{{ _.BaseURL }}/users","name":"create","description":"","method":"POST","body":{"mimeType":"application/json","text":"{\n\t\"nome\": \"Idyl Icaro\"\n}"},"parameters":[],"headers":[{"name":"Content-Type","value":"application/json","id":"pair_d42b8a4c4979491d897ac0aefae39a59"}],"authentication":{},"metaSortKey":-1619132099575,"isPrivate":false,"settingStoreCookies":true,"settingSendCookies":true,"settingDisableRenderRequestBody":false,"settingEncodeUrl":true,"settingRebuildPath":true,"settingFollowRedirects":"global","_type":"request"},{"_id":"req_690505c259324759ad5d96f3214df430","parentId":"fld_7c17905fe9454434a797cd6b98505b63","modified":1619132109113,"created":1618951427766,"url":"{{ _.BaseURL }}/users/1","name":"update","description":"","method":"PUT","body":{"mimeType":"application/json","text":"{\n\t\"nome\": \"Idyl Icaro\"\n}"},"parameters":[],"headers":[{"name":"Content-Type","value":"application/json","id":"pair_f21d32d9ef1e448094f5802d01038520"}],"authentication":{},"metaSortKey":-1619132099550,"isPrivate":false,"settingStoreCookies":true,"settingSendCookies":true,"settingDisableRenderRequestBody":false,"settingEncodeUrl":true,"settingRebuildPath":true,"settingFollowRedirects":"global","_type":"request"},{"_id":"req_98611be7dfa14a0aafd49b135c9517b0","parentId":"fld_7c17905fe9454434a797cd6b98505b63","modified":1619132120594,"created":1619132099525,"url":"{{ _.BaseURL }}/users/1","name":"delete","description":"","method":"DELETE","body":{},"parameters":[],"headers":[],"authentication":{},"metaSortKey":-1619132099525,"isPrivate":false,"settingStoreCookies":true,"settingSendCookies":true,"settingDisableRenderRequestBody":false,"settingEncodeUrl":true,"settingRebuildPath":true,"settingFollowRedirects":"global","_type":"request"},{"_id":"req_de02efc72a824d398124191eba1dd219","parentId":"fld_99563d6c28324f7e8c57d64111df2c8a","modified":1619132171406,"created":1619132164946,"url":"{{ _.BaseURL }}/products","name":"findAll","description":"","method":"GET","body":{},"parameters":[],"headers":[],"authentication":{},"metaSortKey":-1619132099625,"isPrivate":false,"settingStoreCookies":true,"settingSendCookies":true,"settingDisableRenderRequestBody":false,"settingEncodeUrl":true,"settingRebuildPath":true,"settingFollowRedirects":"global","_type":"request"},{"_id":"fld_99563d6c28324f7e8c57d64111df2c8a","parentId":"wrk_2a18ee995e4e460d8a576e4d8fe5852b","modified":1619132164926,"created":1619132164926,"name":"product","description":"","environment":{},"environmentPropertyOrder":null,"metaSortKey":-1615716214485.5,"_type":"request_group"},{"_id":"req_674223f7e0214053b00f318f1a4c2f56","parentId":"fld_99563d6c28324f7e8c57d64111df2c8a","modified":1619132178845,"created":1619132164950,"url":"{{ _.BaseURL }}/products/1","name":"findOneById","description":"","method":"GET","body":{},"parameters":[],"headers":[],"authentication":{},"metaSortKey":-1619132099600,"isPrivate":false,"settingStoreCookies":true,"settingSendCookies":true,"settingDisableRenderRequestBody":false,"settingEncodeUrl":true,"settingRebuildPath":true,"settingFollowRedirects":"global","_type":"request"},{"_id":"req_86e9e8a508df4de9b0cb74af376c34f2","parentId":"fld_99563d6c28324f7e8c57d64111df2c8a","modified":1619132224385,"created":1619132164935,"url":"{{ _.BaseURL }}/products","name":"create","description":"","method":"POST","body":{"mimeType":"application/json","text":"{\n\t\"nome\": \"kawi\",\n\t\"preco\":\"23.0\"\n}"},"parameters":[],"headers":[{"name":"Content-Type","value":"application/json","id":"pair_d42b8a4c4979491d897ac0aefae39a59"}],"authentication":{},"metaSortKey":-1619132099575,"isPrivate":false,"settingStoreCookies":true,"settingSendCookies":true,"settingDisableRenderRequestBody":false,"settingEncodeUrl":true,"settingRebuildPath":true,"settingFollowRedirects":"global","_type":"request"},{"_id":"req_d02864a819b84f67ad8265427c970835","parentId":"fld_99563d6c28324f7e8c57d64111df2c8a","modified":1619132263050,"created":1619132164941,"url":"{{ _.BaseURL }}/products/2","name":"update","description":"","method":"PUT","body":{"mimeType":"application/json","text":"{\n\t\"nome\": \"kawi\",\n\t\"preco\":\"20.0\"\n}"},"parameters":[],"headers":[{"name":"Content-Type","value":"application/json","id":"pair_f21d32d9ef1e448094f5802d01038520"}],"authentication":{},"metaSortKey":-1619132099550,"isPrivate":false,"settingStoreCookies":true,"settingSendCookies":true,"settingDisableRenderRequestBody":false,"settingEncodeUrl":true,"settingRebuildPath":true,"settingFollowRedirects":"global","_type":"request"},{"_id":"req_4aeaa174a622429eb229308f624bfd52","parentId":"fld_99563d6c28324f7e8c57d64111df2c8a","modified":1619132306589,"created":1619132164953,"url":"{{ _.BaseURL }}/products/3","name":"delete","description":"","method":"DELETE","body":{},"parameters":[],"headers":[],"authentication":{},"metaSortKey":-1619132099525,"isPrivate":false,"settingStoreCookies":true,"settingSendCookies":true,"settingDisableRenderRequestBody":false,"settingEncodeUrl":true,"settingRebuildPath":true,"settingFollowRedirects":"global","_type":"request"},{"_id":"req_221bdd2f769f499cae30ee12f25246a6","parentId":"fld_221e514ade0f4b75a82a209fe6fb1700","modified":1619132328740,"created":1619132323070,"url":"{{ _.BaseURL }}/sales","name":"findAll","description":"","method":"GET","body":{},"parameters":[],"headers":[],"authentication":{},"metaSortKey":-1619132099625,"isPrivate":false,"settingStoreCookies":true,"settingSendCookies":true,"settingDisableRenderRequestBody":false,"settingEncodeUrl":true,"settingRebuildPath":true,"settingFollowRedirects":"global","_type":"request"},{"_id":"fld_221e514ade0f4b75a82a209fe6fb1700","parentId":"wrk_2a18ee995e4e460d8a576e4d8fe5852b","modified":1619132323041,"created":1619132323041,"name":"sale","description":"","environment":{},"environmentPropertyOrder":null,"metaSortKey":-1614101878885.25,"_type":"request_group"},{"_id":"req_419a71f178304ce2bca659599d45620b","parentId":"fld_221e514ade0f4b75a82a209fe6fb1700","modified":1619132503328,"created":1619132323073,"url":"{{ _.BaseURL }}/sales/2","name":"findOneById","description":"","method":"GET","body":{},"parameters":[],"headers":[],"authentication":{},"metaSortKey":-1619132099600,"isPrivate":false,"settingStoreCookies":true,"settingSendCookies":true,"settingDisableRenderRequestBody":false,"settingEncodeUrl":true,"settingRebuildPath":true,"settingFollowRedirects":"global","_type":"request"},{"_id":"req_72ffe45e966849ff8c9b9bd550462c1a","parentId":"fld_221e514ade0f4b75a82a209fe6fb1700","modified":1619132559456,"created":1619132352986,"url":"{{ _.BaseURL }}/sales","name":"findByFilters","description":"","method":"GET","body":{},"parameters":[{"name":"id_user","value":"","description":"","id":"pair_c3acf98de7274c31b48e40aebf5ce844"},{"name":"id_product","value":"2","description":"","id":"pair_bfac11307ca9444c8ed4565a747feac4"}],"headers":[],"authentication":{},"metaSortKey":-1619132099587.5,"isPrivate":false,"settingStoreCookies":true,"settingSendCookies":true,"settingDisableRenderRequestBody":false,"settingEncodeUrl":true,"settingRebuildPath":true,"settingFollowRedirects":"global","_type":"request"},{"_id":"req_2756bf2a6a9c45968ce9fbac389106cc","parentId":"fld_221e514ade0f4b75a82a209fe6fb1700","modified":1619132488660,"created":1619132323053,"url":"{{ _.BaseURL }}/sales","name":"create","description":"","method":"POST","body":{"mimeType":"application/json","text":"{\n\t\"id_produto\": \"2\",\n\t\"id_usuario\":\"1\"\n}"},"parameters":[],"headers":[{"name":"Content-Type","value":"application/json","id":"pair_d42b8a4c4979491d897ac0aefae39a59"}],"authentication":{},"metaSortKey":-1619132099575,"isPrivate":false,"settingStoreCookies":true,"settingSendCookies":true,"settingDisableRenderRequestBody":false,"settingEncodeUrl":true,"settingRebuildPath":true,"settingFollowRedirects":"global","_type":"request"},{"_id":"req_a75cca45426044b7849ed1fdfd1b29d7","parentId":"fld_221e514ade0f4b75a82a209fe6fb1700","modified":1619132460496,"created":1619132323067,"url":"{{ _.BaseURL }}/sales/1","name":"update","description":"","method":"PUT","body":{"mimeType":"application/json","text":"{\n\t\"id_produto\": \"2\",\n\t\"id_usuario\":\"1\"\n}"},"parameters":[],"headers":[{"name":"Content-Type","value":"application/json","id":"pair_f21d32d9ef1e448094f5802d01038520"}],"authentication":{},"metaSortKey":-1619132099550,"isPrivate":false,"settingStoreCookies":true,"settingSendCookies":true,"settingDisableRenderRequestBody":false,"settingEncodeUrl":true,"settingRebuildPath":true,"settingFollowRedirects":"global","_type":"request"},{"_id":"req_68732cafeaa7489d931348db8c8c2cfa","parentId":"fld_221e514ade0f4b75a82a209fe6fb1700","modified":1619132478353,"created":1619132323076,"url":"{{ _.BaseURL }}/sales/1","name":"delete","description":"","method":"DELETE","body":{},"parameters":[],"headers":[],"authentication":{},"metaSortKey":-1619132099525,"isPrivate":false,"settingStoreCookies":true,"settingSendCookies":true,"settingDisableRenderRequestBody":false,"settingEncodeUrl":true,"settingRebuildPath":true,"settingFollowRedirects":"global","_type":"request"},{"_id":"env_5b88a4e466712a876c51fd14197502d03df73816","parentId":"wrk_2a18ee995e4e460d8a576e4d8fe5852b","modified":1618857894251,"created":1618857522791,"name":"Base Environment","data":{"BaseURL":"http://localhost:5050/api"},"dataPropertyOrder":{"&":["BaseURL"]},"color":null,"isPrivate":false,"metaSortKey":1618857522791,"_type":"environment"},{"_id":"jar_5b88a4e466712a876c51fd14197502d03df73816","parentId":"wrk_2a18ee995e4e460d8a576e4d8fe5852b","modified":1618857522795,"created":1618857522795,"name":"Default Jar","cookies":[],"_type":"cookie_jar"},{"_id":"spc_d077da9a1276461fa938f7dbed93430a","parentId":"wrk_2a18ee995e4e460d8a576e4d8fe5852b","modified":1618857521737,"created":1618857521737,"fileName":"trainee itatech 2021","contents":"","contentType":"yaml","_type":"api_spec"}]}